ljbtools/__init__.py
ljbtools/analyse_utils.py
ljbtools/common_utils.py
ljbtools/date_utils.py
ljbtools/fetch_utils.py
ljbtools/mongo_utils.py
ljbtools/redis_utils.py
ljbtools-0.2.5.dist-info/licenses/LICENSE
ljbtools-0.2.5.dist-info/METADATA
ljbtools-0.2.5.dist-info/WHEEL
ljbtools-0.2.5.dist-info/top_level.txt
ljbtools-0.2.5.dist-info/RECORD
