Metadata-Version: 2.4
Name: ljbtools
Version: 0.2.5
Summary: personal package
Home-page: https://github.com/Jianbin-Li/ljbtools
Author: Jianbin Li
Author-email: 491256499@qq.com
Classifier: Programming Language :: Python :: 3
Classifier: License :: OSI Approved :: MIT License
Classifier: Operating System :: OS Independent
Requires-Python: >=3.8
License-File: LICENSE
Requires-Dist: pycryptodome==3.10.1
Requires-Dist: curl-cffi==0.7.4
Dynamic: author
Dynamic: author-email
Dynamic: classifier
Dynamic: description
Dynamic: description-content-type
Dynamic: home-page
Dynamic: license-file
Dynamic: requires-dist
Dynamic: requires-python
Dynamic: summary
